PCsrc.sv
module PCsrc #(
    parameter Data_width=32
) (
    input [Data_width-1:0] branch_PC, //first port
    input [Data_width-1:0] inc_PC, //second port 
    input sel, 
    output [Data_width-1:0] out
);
    assign out = sel ? branch_PC:inc_PC;
endmodule

PCReg.sv
module PCReg #(
    parameter WIDTH = 32
)(
    input logic clk,
    input logic rst,
    input logic [WIDTH-1:0] next_PC,
    output logic [WIDTH-1:0] PC
);

    always_ff @(posedge clk) begin
        if (rst) PC <= {WIDTH{1'b0}}; 
        else PC <= next_PC;
    end

endmodule

alu.sv
module alu #(
    parameter Data_width=32
) (
    input [Data_width-1:0] aluop1,aluop2,
    input [2:0] aluctrl, 
    output reg [Data_width-1:0] aluout,// it should be a 'reg' type to be assigned with value inside always_comb
    output reg eq //same as above
);  
    always_comb begin 
        case(aluctrl)
        3'b0: aluout=aluop1+aluop2; 
        3'b1: eq=(aluop1==aluop2); 
        default : begin
            aluout={Data_width{1'b0}};
            eq=1'b0; 
        end 
        endcase
    end 
endmodule

regfile.sv
module regfile #(
    parameter Data_width=32,Addr_width=5
) (
    input clk, 
    input [Addr_width-1:0] ad1,ad2,ad3,
    input we3,
    input [Data_width-1:0] wd3,
    output [Data_width-1:0] rd1,rd2,
    output [Data_width-1:0] a0 
);
    //Declare 32 registers each 32 bits wide
    logic [Data_width-1:0] register_array [2**Addr_width-1:0];

    //asychronous READ ports
    assign rd1=register_array[ad1];
    assign rd2=register_array[ad2];
    assign a0=register_array[{{Addr_width-4{1'b0}},4'b1010}]; //a0 at position 10 
    //synchronous WRITE ports 
    always_ff @(posedge clk)begin
        if(we3) begin 
            register_array[ad3]<=wd3; 
        end 
    end 
endmodule

mux2to1.sv
module mux2to1 #(
    parameter Data_width=32
) (
    input [Data_width-1:0] d0, //first port
    input [Data_width-1:0] d1, //second port 
    input sel, 
    output [Data_width-1:0] out
);
    assign out = sel ? d1:d0;
endmodule

sext.sv
module sext #(
    parameter WIDTH = 32,
    parameter IN_WIDTH = 12
)(
    input logic [WIDTH-1:0] instr,
    input logic [IN_WIDTH-1:0] immsrc,
    output logic [WIDTH-1:0] imm_out
);

always_comb begin
    case (instr[6:2])
        5'b00100: imm_out = {{(WIDTH-IN_WIDTH){immsrc[IN_WIDTH]}}, {immsrc}} ;
        5'b11000: imm_out = {{(WIDTH-IN_WIDTH-1){immsrc[IN_WIDTH]}},{immsrc},{1'b0}} ;
    endcase
end

endmodule

ctr_unit.sv
module ctr_unit #(
    parameter IN_WIDTH = 32
)(
    input logic eq,
    input logic [IN_WIDTH-1:0] instr,
    output logic RegWrite,
    output logic [2:0] ALUctrl,
    output logic ALUsrc,
    output logic [11:0] ImmSrc,
    output logic PCsrc
);

always_comb begin
    case (instr[6:2])
        5'b00100: begin // addi
            RegWrite = 1;
            ALUctrl = 3'b0;
            ALUsrc = 1;
            ImmSrc = instr[31:20];
            PCsrc = 0;
        end
        5'b11000: begin // bne
            RegWrite = 0;
            ALUctrl = 3'b1;
            ALUsrc = 0;
            ImmSrc = {instr[31],instr[7],instr[30:25],instr[11:8]};
            if (eq) PCsrc = 0; 
            else PCsrc = 1;
        end
    endcase
end 

endmodule

instr_mem.sv
module instr_mem #(
    parameter WIDTH = 32,
    parameter ADDR_WIDTH = 32,
    parameter RAMZ = 32,
    parameter intFile = "instr.mem"
)(
    input logic [ADDR_WIDTH-1:0] a,
    output logic [WIDTH-1:0] rd
);

logic [WIDTH-1:0] ram [0:RAMZ-1];
initial $readmemh(intFile,ram,0,31);
assign rd = ram[a];

endmodule

riscv.sv
module riscv #(
    parameter WIDTH = 32
)(
    input logic clk,
    input logic rst,
    output logic [WIDTH-1:0] a0
);

logic [WIDTH-1:0] pc;
logic [WIDTH-1:0] next_pc;
logic [WIDTH-1:0] branch_pc;
logic [WIDTH-1:0] inc_pc;
logic [WIDTH-1:0] instr;
logic RegWrite;
logic [2:0] ALUctrl;
logic ALUsrc;
logic [11:0] ImmSrc;
logic PCsrc;
logic [WIDTH-1:0] immop;
logic [WIDTH-1:0] aluop1;
logic [WIDTH-1:0] aluop2;
logic [WIDTH-1:0] regop2;
logic [WIDTH-1:0] aluout;
logic eq;
logic [WIDTH-1:0] rs1;
logic [WIDTH-1:0] rs2;
logic [WIDTH-1:0] rd;

instr_mem my_instr_mem (
    .a(pc),
    .rd(instr)
);

ctr_unit my_ctr_unit (
    .instr(instr),
    .eq(eq),
    .RegWrite(RegWrite),
    .ALUctrl(ALUctrl),
    .ALUsrc(ALUsrc),
    .ImmSrc(ImmSrc),
    .PCsrc(PCsrc)
);

sext my_sext(
    .instr(instr),
    .immsrc(ImmSrc),
    .imm_out(immop)
);

//mux for alu 
mux2to1 my_mux2to1(
    .d0(regop2),
    .d1(immop),
    .out(aluop2)
);

//register file
regfile my_regfile(
    .clk(clk),
    .ad1(rs1),
    .ad2(rs2),
    .ad3(rd), 
    .we3(RegWrite),
    .wd3(aluout),
    .rd1(aluop1),
    .rd2(regop2),
    .a0(a0)
);
//alu
alu my_alu(
    .aluop1(aluop1),
    .aluop2(aluop2),
    .aluout(aluout),
    .eq(eq)
);

PCReg my_PCReg(
    .PC(pc),
    .next_PC(next_pc)
);
    
PCsrc my_PCsrc(
    .branch_PC(branch_pc),
    .inc_PC(inc_pc),
    .out(next_pc)
);


endmodule

riscv.vcd
$version Generated by VerilatedVcd $end
$date Tue Nov 21 18:03:57 2023 $end
$timescale 1ps $end

 $scope module TOP $end
  $var wire 32 x a0 [31:0] $end
  $var wire  1 v clk $end
  $var wire  1 w rst $end
  $scope module riscv $end
   $var wire  3 I ALUctrl [2:0] $end
   $var wire  1 J ALUsrc $end
   $var wire 12 K ImmSrc [11:0] $end
   $var wire  1 L PCsrc $end
   $var wire  1 H RegWrite $end
   $var wire 32 y WIDTH [31:0] $end
   $var wire 32 x a0 [31:0] $end
   $var wire 32 N aluop1 [31:0] $end
   $var wire 32 O aluop2 [31:0] $end
   $var wire 32 Q aluout [31:0] $end
   $var wire 32 E branch_pc [31:0] $end
   $var wire  1 v clk $end
   $var wire  1 R eq $end
   $var wire 32 M immop [31:0] $end
   $var wire 32 F inc_pc [31:0] $end
   $var wire 32 G instr [31:0] $end
   $var wire 32 D next_pc [31:0] $end
   $var wire 32 C pc [31:0] $end
   $var wire  5 U rd [4:0] $end
   $var wire 32 P regop2 [31:0] $end
   $var wire  5 S rs1 [4:0] $end
   $var wire  5 T rs2 [4:0] $end
   $var wire  1 w rst $end
   $scope module my_PCReg $end
    $var wire 32 C PC [31:0] $end
    $var wire 32 y WIDTH [31:0] $end
    $var wire  1 v clk $end
    $var wire 32 D next_PC [31:0] $end
    $var wire  1 w rst $end
   $upscope $end
   $scope module my_PCsrc $end
    $var wire 32 y Data_width [31:0] $end
    $var wire 32 E branch_PC [31:0] $end
    $var wire 32 F inc_PC [31:0] $end
    $var wire 32 D out [31:0] $end
    $var wire  1 L sel $end
   $upscope $end
   $scope module my_alu $end
    $var wire 32 y Data_width [31:0] $end
    $var wire  3 I aluctrl [2:0] $end
    $var wire 32 N aluop1 [31:0] $end
    $var wire 32 O aluop2 [31:0] $end
    $var wire 32 Q aluout [31:0] $end
    $var wire  1 R eq $end
   $upscope $end
   $scope module my_ctr_unit $end
    $var wire  3 I ALUctrl [2:0] $end
    $var wire  1 J ALUsrc $end
    $var wire 32 y IN_WIDTH [31:0] $end
    $var wire 12 K ImmSrc [11:0] $end
    $var wire  1 L PCsrc $end
    $var wire  1 H RegWrite $end
    $var wire  1 R eq $end
    $var wire 32 G instr [31:0] $end
   $upscope $end
   $scope module my_instr_mem $end
    $var wire 32 y ADDR_WIDTH [31:0] $end
    $var wire 32 y RAMZ [31:0] $end
    $var wire 32 y WIDTH [31:0] $end
    $var wire 32 C a [31:0] $end
    $var wire 72 z intFile [71:0] $end
    $var wire 32 # ram[0] [31:0] $end
    $var wire 32 - ram[10] [31:0] $end
    $var wire 32 . ram[11] [31:0] $end
    $var wire 32 / ram[12] [31:0] $end
    $var wire 32 0 ram[13] [31:0] $end
    $var wire 32 1 ram[14] [31:0] $end
    $var wire 32 2 ram[15] [31:0] $end
    $var wire 32 3 ram[16] [31:0] $end
    $var wire 32 4 ram[17] [31:0] $end
    $var wire 32 5 ram[18] [31:0] $end
    $var wire 32 6 ram[19] [31:0] $end
    $var wire 32 $ ram[1] [31:0] $end
    $var wire 32 7 ram[20] [31:0] $end
    $var wire 32 8 ram[21] [31:0] $end
    $var wire 32 9 ram[22] [31:0] $end
    $var wire 32 : ram[23] [31:0] $end
    $var wire 32 ; ram[24] [31:0] $end
    $var wire 32 < ram[25] [31:0] $end
    $var wire 32 = ram[26] [31:0] $end
    $var wire 32 > ram[27] [31:0] $end
    $var wire 32 ? ram[28] [31:0] $end
    $var wire 32 @ ram[29] [31:0] $end
    $var wire 32 % ram[2] [31:0] $end
    $var wire 32 A ram[30] [31:0] $end
    $var wire 32 B ram[31] [31:0] $end
    $var wire 32 & ram[3] [31:0] $end
    $var wire 32 ' ram[4] [31:0] $end
    $var wire 32 ( ram[5] [31:0] $end
    $var wire 32 ) ram[6] [31:0] $end
    $var wire 32 * ram[7] [31:0] $end
    $var wire 32 + ram[8] [31:0] $end
    $var wire 32 , ram[9] [31:0] $end
    $var wire 32 G rd [31:0] $end
   $upscope $end
   $scope module my_mux2to1 $end
    $var wire 32 y Data_width [31:0] $end
    $var wire 32 P d0 [31:0] $end
    $var wire 32 M d1 [31:0] $end
    $var wire 32 O out [31:0] $end
    $var wire  1 J sel $end
   $upscope $end
   $scope module my_regfile $end
    $var wire 32 } Addr_width [31:0] $end
    $var wire 32 y Data_width [31:0] $end
    $var wire 32 x a0 [31:0] $end
    $var wire  5 S ad1 [4:0] $end
    $var wire  5 T ad2 [4:0] $end
    $var wire  5 U ad3 [4:0] $end
    $var wire  1 v clk $end
    $var wire 32 N rd1 [31:0] $end
    $var wire 32 P rd2 [31:0] $end
    $var wire 32 V register_array[0] [31:0] $end
    $var wire 32 ` register_array[10] [31:0] $end
    $var wire 32 a register_array[11] [31:0] $end
    $var wire 32 b register_array[12] [31:0] $end
    $var wire 32 c register_array[13] [31:0] $end
    $var wire 32 d register_array[14] [31:0] $end
    $var wire 32 e register_array[15] [31:0] $end
    $var wire 32 f register_array[16] [31:0] $end
    $var wire 32 g register_array[17] [31:0] $end
    $var wire 32 h register_array[18] [31:0] $end
    $var wire 32 i register_array[19] [31:0] $end
    $var wire 32 W register_array[1] [31:0] $end
    $var wire 32 j register_array[20] [31:0] $end
    $var wire 32 k register_array[21] [31:0] $end
    $var wire 32 l register_array[22] [31:0] $end
    $var wire 32 m register_array[23] [31:0] $end
    $var wire 32 n register_array[24] [31:0] $end
    $var wire 32 o register_array[25] [31:0] $end
    $var wire 32 p register_array[26] [31:0] $end
    $var wire 32 q register_array[27] [31:0] $end
    $var wire 32 r register_array[28] [31:0] $end
    $var wire 32 s register_array[29] [31:0] $end
    $var wire 32 X register_array[2] [31:0] $end
    $var wire 32 t register_array[30] [31:0] $end
    $var wire 32 u register_array[31] [31:0] $end
    $var wire 32 Y register_array[3] [31:0] $end
    $var wire 32 Z register_array[4] [31:0] $end
    $var wire 32 [ register_array[5] [31:0] $end
    $var wire 32 \ register_array[6] [31:0] $end
    $var wire 32 ] register_array[7] [31:0] $end
    $var wire 32 ^ register_array[8] [31:0] $end
    $var wire 32 _ register_array[9] [31:0] $end
    $var wire 32 Q wd3 [31:0] $end
    $var wire  1 H we3 $end
   $upscope $end
   $scope module my_sext $end
    $var wire 32 ~ IN_WIDTH [31:0] $end
    $var wire 32 y WIDTH [31:0] $end
    $var wire 32 M imm_out [31:0] $end
    $var wire 12 K immsrc [11:0] $end
    $var wire 32 G instr [31:0] $end
   $upscope $end
  $upscope $end
 $upscope $end
$enddefinitions $end


#0
b00000000000000000000000000000000 #
b00000000000000000000000000000000 $
b00000000000000000000000000000000 %
b00000000000000000000000000000000 &
b00000000000000000000000000000000 '
b00000000000000000000000000000000 (
b00000000000000000000000000000000 )
b00000000000000000000000000000000 *
b00000000000000000000000000000000 +
b00000000000000000000000000000000 ,
b00000000000000000000000000000000 -
b00000000000000000000000000000000 .
b00000000000000000000000000000000 /
b00000000000000000000000000000000 0
b00000000000000000000000000000000 1
b00000000000000000000000000000000 2
b00000000000000000000000000000000 3
b00000000000000000000000000000000 4
b00000000000000000000000000000000 5
b00000000000000000000000000000000 6
b00000000000000000000000000000000 7
b00000000000000000000000000000000 8
b00000000000000000000000000000000 9
b00000000000000000000000000000000 :
b00000000000000000000000000000000 ;
b00000000000000000000000000000000 <
b00000000000000000000000000000000 =
b00000000000000000000000000000000 >
b00000000000000000000000000000000 ?
b00000000000000000000000000000000 @
b00000000000000000000000000000000 A
b00000000000000000000000000000000 B
b00000000000000000000000000000000 C
b00000000000000000000000000000100 D
b00000000000000000000000000000000 E
b00000000000000000000000000000100 F
b00000000000000000000000000000000 G
0H
b000 I
0J
b000000000000 K
0L
b00000000000000000000000000000000 M
b00000000000000000000000000000000 N
b00000000000000000000000000000000 O
b00000000000000000000000000000000 P
b00000000000000000000000000000000 Q
0R
b00000 S
b00000 T
b00000 U
b00000000000000000000000000000000 V
b00000000000000000000000000000000 W
b00000000000000000000000000000000 X
b00000000000000000000000000000000 Y
b00000000000000000000000000000000 Z
b00000000000000000000000000000000 [
b00000000000000000000000000000000 \
b00000000000000000000000000000000 ]
b00000000000000000000000000000000 ^
b00000000000000000000000000000000 _
b00000000000000000000000000000000 `
b00000000000000000000000000000000 a
b00000000000000000000000000000000 b
b00000000000000000000000000000000 c
b00000000000000000000000000000000 d
b00000000000000000000000000000000 e
b00000000000000000000000000000000 f
b00000000000000000000000000000000 g
b00000000000000000000000000000000 h
b00000000000000000000000000000000 i
b00000000000000000000000000000000 j
b00000000000000000000000000000000 k
b00000000000000000000000000000000 l
b00000000000000000000000000000000 m
b00000000000000000000000000000000 n
b00000000000000000000000000000000 o
b00000000000000000000000000000000 p
b00000000000000000000000000000000 q
b00000000000000000000000000000000 r
b00000000000000000000000000000000 s
b00000000000000000000000000000000 t
b00000000000000000000000000000000 u
1v
0w
b00000000000000000000000000000000 x
b00000000000000000000000000100000 y
b011010010110111001110011011101000111001000101110011011010110010101101101 z
b00000000000000000000000000000101 }
b00000000000000000000000000001100 ~
#1
b00001111111100000000001100010011 #
b00000000000000000000010100010011 '
b00000000000000000000010110010011 +
b00000000000001011000010100010011 /
b00000000000101011000010110010011 3
b11111110011001011001110011100011 7
b11111110000000110001100011100011 ;
b00000000000000000000000011111111 E
b00001111111100000000001100010011 G
1H
1J
b000011111111 K
b00000000000000000000000011111111 M
b00000000000000000000000011111111 O
b00000000000000000000000011111111 Q
b11111 T
b00110 U
0v
#2
b00000000000000000000000000000100 C
b00000000000000000000000000001000 D
b00000000000000000000000000000100 E
b00000000000000000000000000001000 F
b00000000000000000000010100010011 G
b000000000000 K
b00000000000000000000000000000000 M
b00000000000000000000000000000000 O
b00000000000000000000000000000000 Q
b00000 T
b01010 U
b00000000000000000000000011111111 \
1v
#3
0v
#4
b00000000000000000000000000001000 C
b00000000000000000000000000001100 D
b00000000000000000000000000001000 E
b00000000000000000000000000001100 F
b00000000000000000000010110010011 G
b01011 U
1v
#5
0v
#6
b00000000000000000000000000001100 C
b00000000000000000000000000010000 D
b00000000000000000000000000001100 E
b00000000000000000000000000010000 F
b00000000000001011000010100010011 G
b01011 S
b01010 U
1v
#7
0v
#8
b00000000000000000000000000010000 C
b00000000000000000000000000010100 D
b00000000000000000000000000010001 E
b00000000000000000000000000010100 F
b00000000000101011000010110010011 G
b000000000001 K
b00000000000000000000000000000001 M
b00000000000000000000000000000001 O
b00000000000000000000000000000001 Q
b00001 T
b01011 U
1v
#9
0v
#10
b00000000000000000000000000010100 C
b00000000000000000000000000001100 D
b00000000000000000000000000001100 E
b00000000000000000000000000011000 F
b11111110011001011001110011100011 G
0H
b001 I
0J
b111111111000 K
1L
b11111111111111111111111111111000 M
b00000000000000000000000000000001 N
b00000000000000000000000011111111 O
b00000000000000000000000011111111 P
b00110 T
b11001 U
b00000000000000000000000000000001 a
1v
#11
0v
#12
b00000000000000000000000000001100 C
b00000000000000000000000000010000 D
b00000000000000000000000000010000 F
b00000000000001011000010100010011 G
1H
b000 I
1J
b000000000000 K
0L
b00000000000000000000000000000000 M
b00000000000000000000000000000000 O
b00000000000000000000000000000000 P
b00000 T
b01010 U
1v
#13
0v
#14
b00000000000000000000000000010000 C
b00000000000000000000000000010100 D
b00000000000000000000000000010001 E
b00000000000000000000000000010100 F
b00000000000101011000010110010011 G
b000000000001 K
b00000000000000000000000000000001 M
b00000000000000000000000000000001 O
b00000000000000000000000000000010 Q
b00001 T
b01011 U
b00000000000000000000000000000001 `
1v
#15
0v
#16
b00000000000000000000000000010100 C
b00000000000000000000000000001100 D
b00000000000000000000000000001100 E
b00000000000000000000000000011000 F
b11111110011001011001110011100011 G
0H
b001 I
0J
b111111111000 K
1L
b11111111111111111111111111111000 M
b00000000000000000000000000000010 N
b00000000000000000000000011111111 O
b00000000000000000000000011111111 P
b00110 T
b11001 U
b00000000000000000000000000000010 a
1v
#17
0v
#18
b00000000000000000000000000001100 C
b00000000000000000000000000010000 D
b00000000000000000000000000010000 F
b00000000000001011000010100010011 G
1H
b000 I
1J
b000000000000 K
0L
b00000000000000000000000000000000 M
b00000000000000000000000000000000 O
b00000000000000000000000000000000 P
b00000 T
b01010 U
1v
#19
0v
#20
b00000000000000000000000000010000 C
b00000000000000000000000000010100 D
b00000000000000000000000000010001 E
b00000000000000000000000000010100 F
b00000000000101011000010110010011 G
b000000000001 K
b00000000000000000000000000000001 M
b00000000000000000000000000000001 O
b00000000000000000000000000000011 Q
b00001 T
b01011 U
b00000000000000000000000000000010 `
1v
#21
0v
#22
b00000000000000000000000000010100 C
b00000000000000000000000000001100 D
b00000000000000000000000000001100 E
b00000000000000000000000000011000 F
b11111110011001011001110011100011 G
0H
b001 I
0J
b111111111000 K
1L
b11111111111111111111111111111000 M
b00000000000000000000000000000011 N
b00000000000000000000000011111111 O
b00000000000000000000000011111111 P
b00110 T
b11001 U
b00000000000000000000000000000011 a
1v
#23
0v
#24
b00000000000000000000000000001100 C
b00000000000000000000000000010000 D
b00000000000000000000000000010000 F
b00000000000001011000010100010011 G
1H
b000 I
1J
b000000000000 K
0L
b00000000000000000000000000000000 M
b00000000000000000000000000000000 O
b00000000000000000000000000000000 P
b00000 T
b01010 U
1v
#25
0v
#26
b00000000000000000000000000010000 C
b00000000000000000000000000010100 D
b00000000000000000000000000010001 E
b00000000000000000000000000010100 F
b00000000000101011000010110010011 G
b000000000001 K
b00000000000000000000000000000001 M
b00000000000000000000000000000001 O
b00000000000000000000000000000100 Q
b00001 T
b01011 U
b00000000000000000000000000000011 `
1v
#27
0v
#28
b00000000000000000000000000010100 C
b00000000000000000000000000001100 D
b00000000000000000000000000001100 E
b00000000000000000000000000011000 F
b11111110011001011001110011100011 G
0H
b001 I
0J
b111111111000 K
1L
b11111111111111111111111111111000 M
b00000000000000000000000000000100 N
b00000000000000000000000011111111 O
b00000000000000000000000011111111 P
b00110 T
b11001 U
b00000000000000000000000000000100 a
1v
#29
0v
#30
b00000000000000000000000000001100 C
b00000000000000000000000000010000 D
b00000000000000000000000000010000 F
b00000000000001011000010100010011 G
1H
b000 I
1J
b000000000000 K
0L
b00000000000000000000000000000000 M
b00000000000000000000000000000000 O
b00000000000000000000000000000000 P
b00000 T
b01010 U
1v
#31
0v
#32
b00000000000000000000000000010000 C
b00000000000000000000000000010100 D
b00000000000000000000000000010001 E
b00000000000000000000000000010100 F
b00000000000101011000010110010011 G
b000000000001 K
b00000000000000000000000000000001 M
b00000000000000000000000000000001 O
b00000000000000000000000000000101 Q
b00001 T
b01011 U
b00000000000000000000000000000100 `
1v
#33
0v
#34
b00000000000000000000000000010100 C
b00000000000000000000000000001100 D
b00000000000000000000000000001100 E
b00000000000000000000000000011000 F
b11111110011001011001110011100011 G
0H
b001 I
0J
b111111111000 K
1L
b11111111111111111111111111111000 M
b00000000000000000000000000000101 N
b00000000000000000000000011111111 O
b00000000000000000000000011111111 P
b00110 T
b11001 U
b00000000000000000000000000000101 a
1v
#35
0v
#36
b00000000000000000000000000001100 C
b00000000000000000000000000010000 D
b00000000000000000000000000010000 F
b00000000000001011000010100010011 G
1H
b000 I
1J
b000000000000 K
0L
b00000000000000000000000000000000 M
b00000000000000000000000000000000 O
b00000000000000000000000000000000 P
b00000 T
b01010 U
1v
#37
0v
#38
b00000000000000000000000000010000 C
b00000000000000000000000000010100 D
b00000000000000000000000000010001 E
b00000000000000000000000000010100 F
b00000000000101011000010110010011 G
b000000000001 K
b00000000000000000000000000000001 M
b00000000000000000000000000000001 O
b00000000000000000000000000000110 Q
b00001 T
b01011 U
b00000000000000000000000000000101 `
1v
#39
0v
#40
b00000000000000000000000000010100 C
b00000000000000000000000000001100 D
b00000000000000000000000000001100 E
b00000000000000000000000000011000 F
b11111110011001011001110011100011 G
0H
b001 I
0J
b111111111000 K
1L
b11111111111111111111111111111000 M
b00000000000000000000000000000110 N
b00000000000000000000000011111111 O
b00000000000000000000000011111111 P
b00110 T
b11001 U
b00000000000000000000000000000110 a
1v
#41
0v
#42
b00000000000000000000000000001100 C
b00000000000000000000000000010000 D
b00000000000000000000000000010000 F
b00000000000001011000010100010011 G
1H
b000 I
1J
b000000000000 K
0L
b00000000000000000000000000000000 M
b00000000000000000000000000000000 O
b00000000000000000000000000000000 P
b00000 T
b01010 U
1v
#43
0v
#44
b00000000000000000000000000010000 C
b00000000000000000000000000010100 D
b00000000000000000000000000010001 E
b00000000000000000000000000010100 F
b00000000000101011000010110010011 G
b000000000001 K
b00000000000000000000000000000001 M
b00000000000000000000000000000001 O
b00000000000000000000000000000111 Q
b00001 T
b01011 U
b00000000000000000000000000000110 `
1v
#45
0v
#46
b00000000000000000000000000010100 C
b00000000000000000000000000001100 D
b00000000000000000000000000001100 E
b00000000000000000000000000011000 F
b11111110011001011001110011100011 G
0H
b001 I
0J
b111111111000 K
1L
b11111111111111111111111111111000 M
b00000000000000000000000000000111 N
b00000000000000000000000011111111 O
b00000000000000000000000011111111 P
b00110 T
b11001 U
b00000000000000000000000000000111 a
1v
#47
0v
#48
b00000000000000000000000000001100 C
b00000000000000000000000000010000 D
b00000000000000000000000000010000 F
b00000000000001011000010100010011 G
1H
b000 I
1J
b000000000000 K
0L
b00000000000000000000000000000000 M
b00000000000000000000000000000000 O
b00000000000000000000000000000000 P
b00000 T
b01010 U
1v
#49
0v
#50
b00000000000000000000000000010000 C
b00000000000000000000000000010100 D
b00000000000000000000000000010001 E
b00000000000000000000000000010100 F
b00000000000101011000010110010011 G
b000000000001 K
b00000000000000000000000000000001 M
b00000000000000000000000000000001 O
b00000000000000000000000000001000 Q
b00001 T
b01011 U
b00000000000000000000000000000111 `
1v
#51
0v
#52
b00000000000000000000000000010100 C
b00000000000000000000000000001100 D
b00000000000000000000000000001100 E
b00000000000000000000000000011000 F
b11111110011001011001110011100011 G
0H
b001 I
0J
b111111111000 K
1L
b11111111111111111111111111111000 M
b00000000000000000000000000001000 N
b00000000000000000000000011111111 O
b00000000000000000000000011111111 P
b00110 T
b11001 U
b00000000000000000000000000001000 a
1v
#53
0v
#54
b00000000000000000000000000001100 C
b00000000000000000000000000010000 D
b00000000000000000000000000010000 F
b00000000000001011000010100010011 G
1H
b000 I
1J
b000000000000 K
0L
b00000000000000000000000000000000 M
b00000000000000000000000000000000 O
b00000000000000000000000000000000 P
b00000 T
b01010 U
1v
#55
0v
#56
b00000000000000000000000000010000 C
b00000000000000000000000000010100 D
b00000000000000000000000000010001 E
b00000000000000000000000000010100 F
b00000000000101011000010110010011 G
b000000000001 K
b00000000000000000000000000000001 M
b00000000000000000000000000000001 O
b00000000000000000000000000001001 Q
b00001 T
b01011 U
b00000000000000000000000000001000 `
1v
#57
0v
#58
b00000000000000000000000000010100 C
b00000000000000000000000000001100 D
b00000000000000000000000000001100 E
b00000000000000000000000000011000 F
b11111110011001011001110011100011 G
0H
b001 I
0J
b111111111000 K
1L
b11111111111111111111111111111000 M
b00000000000000000000000000001001 N
b00000000000000000000000011111111 O
b00000000000000000000000011111111 P
b00110 T
b11001 U
b00000000000000000000000000001001 a
1v
#59
0v
#60
b00000000000000000000000000001100 C
b00000000000000000000000000010000 D
b00000000000000000000000000010000 F
b00000000000001011000010100010011 G
1H
b000 I
1J
b000000000000 K
0L
b00000000000000000000000000000000 M
b00000000000000000000000000000000 O
b00000000000000000000000000000000 P
b00000 T
b01010 U
1v
#61
0v
#62
b00000000000000000000000000010000 C
b00000000000000000000000000010100 D
b00000000000000000000000000010001 E
b00000000000000000000000000010100 F
b00000000000101011000010110010011 G
b000000000001 K
b00000000000000000000000000000001 M
b00000000000000000000000000000001 O
b00000000000000000000000000001010 Q
b00001 T
b01011 U
b00000000000000000000000000001001 `
1v
#63
0v
#64
b00000000000000000000000000010100 C
b00000000000000000000000000001100 D
b00000000000000000000000000001100 E
b00000000000000000000000000011000 F
b11111110011001011001110011100011 G
0H
b001 I
0J
b111111111000 K
1L
b11111111111111111111111111111000 M
b00000000000000000000000000001010 N
b00000000000000000000000011111111 O
b00000000000000000000000011111111 P
b00110 T
b11001 U
b00000000000000000000000000001010 a
1v
#65
0v
#66
b00000000000000000000000000001100 C
b00000000000000000000000000010000 D
b00000000000000000000000000010000 F
b00000000000001011000010100010011 G
1H
b000 I
1J
b000000000000 K
0L
b00000000000000000000000000000000 M
b00000000000000000000000000000000 O
b00000000000000000000000000000000 P
b00000 T
b01010 U
1v
#67
0v
#68
b00000000000000000000000000010000 C
b00000000000000000000000000010100 D
b00000000000000000000000000010001 E
b00000000000000000000000000010100 F
b00000000000101011000010110010011 G
b000000000001 K
b00000000000000000000000000000001 M
b00000000000000000000000000000001 O
b00000000000000000000000000001011 Q
b00001 T
b01011 U
b00000000000000000000000000001010 `
1v
#69
0v
#70
b00000000000000000000000000010100 C
b00000000000000000000000000001100 D
b00000000000000000000000000001100 E
b00000000000000000000000000011000 F
b11111110011001011001110011100011 G
0H
b001 I
0J
b111111111000 K
1L
b11111111111111111111111111111000 M
b00000000000000000000000000001011 N
b00000000000000000000000011111111 O
b00000000000000000000000011111111 P
b00110 T
b11001 U
b00000000000000000000000000001011 a
1v
#71
0v
#72
b00000000000000000000000000001100 C
b00000000000000000000000000010000 D
b00000000000000000000000000010000 F
b00000000000001011000010100010011 G
1H
b000 I
1J
b000000000000 K
0L
b00000000000000000000000000000000 M
b00000000000000000000000000000000 O
b00000000000000000000000000000000 P
b00000 T
b01010 U
1v
#73
0v
#74
b00000000000000000000000000010000 C
b00000000000000000000000000010100 D
b00000000000000000000000000010001 E
b00000000000000000000000000010100 F
b00000000000101011000010110010011 G
b000000000001 K
b00000000000000000000000000000001 M
b00000000000000000000000000000001 O
b00000000000000000000000000001100 Q
b00001 T
b01011 U
b00000000000000000000000000001011 `
1v
#75
0v
#76
b00000000000000000000000000010100 C
b00000000000000000000000000001100 D
b00000000000000000000000000001100 E
b00000000000000000000000000011000 F
b11111110011001011001110011100011 G
0H
b001 I
0J
b111111111000 K
1L
b11111111111111111111111111111000 M
b00000000000000000000000000001100 N
b00000000000000000000000011111111 O
b00000000000000000000000011111111 P
b00110 T
b11001 U
b00000000000000000000000000001100 a
1v
#77
0v
#78
b00000000000000000000000000001100 C
b00000000000000000000000000010000 D
b00000000000000000000000000010000 F
b00000000000001011000010100010011 G
1H
b000 I
1J
b000000000000 K
0L
b00000000000000000000000000000000 M
b00000000000000000000000000000000 O
b00000000000000000000000000000000 P
b00000 T
b01010 U
1v
#79
0v
#80
b00000000000000000000000000010000 C
b00000000000000000000000000010100 D
b00000000000000000000000000010001 E
b00000000000000000000000000010100 F
b00000000000101011000010110010011 G
b000000000001 K
b00000000000000000000000000000001 M
b00000000000000000000000000000001 O
b00000000000000000000000000001101 Q
b00001 T
b01011 U
b00000000000000000000000000001100 `
1v
#81
0v
#82
b00000000000000000000000000010100 C
b00000000000000000000000000001100 D
b00000000000000000000000000001100 E
b00000000000000000000000000011000 F
b11111110011001011001110011100011 G
0H
b001 I
0J
b111111111000 K
1L
b11111111111111111111111111111000 M
b00000000000000000000000000001101 N
b00000000000000000000000011111111 O
b00000000000000000000000011111111 P
b00110 T
b11001 U
b00000000000000000000000000001101 a
1v
#83
0v
#84
b00000000000000000000000000001100 C
b00000000000000000000000000010000 D
b00000000000000000000000000010000 F
b00000000000001011000010100010011 G
1H
b000 I
1J
b000000000000 K
0L
b00000000000000000000000000000000 M
b00000000000000000000000000000000 O
b00000000000000000000000000000000 P
b00000 T
b01010 U
1v
#85
0v
#86
b00000000000000000000000000010000 C
b00000000000000000000000000010100 D
b00000000000000000000000000010001 E
b00000000000000000000000000010100 F
b00000000000101011000010110010011 G
b000000000001 K
b00000000000000000000000000000001 M
b00000000000000000000000000000001 O
b00000000000000000000000000001110 Q
b00001 T
b01011 U
b00000000000000000000000000001101 `
1v
#87
0v
#88
b00000000000000000000000000010100 C
b00000000000000000000000000001100 D
b00000000000000000000000000001100 E
b00000000000000000000000000011000 F
b11111110011001011001110011100011 G
0H
b001 I
0J
b111111111000 K
1L
b11111111111111111111111111111000 M
b00000000000000000000000000001110 N
b00000000000000000000000011111111 O
b00000000000000000000000011111111 P
b00110 T
b11001 U
b00000000000000000000000000001110 a
1v
#89
0v
#90
b00000000000000000000000000001100 C
b00000000000000000000000000010000 D
b00000000000000000000000000010000 F
b00000000000001011000010100010011 G
1H
b000 I
1J
b000000000000 K
0L
b00000000000000000000000000000000 M
b00000000000000000000000000000000 O
b00000000000000000000000000000000 P
b00000 T
b01010 U
1v
#91
0v
