data_mem.sv
module data_mem #(
    parameter WIDTH = 32,
    parameter ADDR_WIDTH = 32,
    parameter RAMZ = 256,
    parameter intFile = "data.mem"
)(
    input logic [ADDR_WIDTH-1:0] a,
    output logic [WIDTH-1:0] rd
);

logic [WIDTH-1:0] ram [0:RAMZ-1];
initial $readmemh(intFile,ram,0,RAMZ-1);
assign rd = ram[a];

endmodule

mux2to1.sv
module mux2to1 #(
    parameter Data_width=32
) (
    input [Data_width-1:0] d0, //first port
    input [Data_width-1:0] d1, //second port 
    input sel, 
    output [Data_width-1:0] out
);
    assign out = sel ? d1:d0;
endmodule

PCReg.sv
module PCReg #(
    parameter WIDTH = 32
)(
    input logic clk,
    input logic rst,
    input logic [WIDTH-1:0] next_PC,
    output logic [WIDTH-1:0] PC
);

    always_ff @(posedge clk) begin
        if (rst) PC <= {WIDTH{1'b0}}; 
        else PC <= next_PC;
    end

endmodule

alu.sv
module alu #(
    parameter Data_width=32
) (
    input [Data_width-1:0] aluop1,aluop2,
    input [2:0] aluctrl, 
    output reg [Data_width-1:0] aluout,// it should be a 'reg' type to be assigned with value inside always_comb
    output reg eq //same as above
);  
    always_comb begin 
        case(aluctrl)
        3'b0: aluout=aluop1+aluop2; 
        3'b1: eq=(aluop1==aluop2); 
        default : begin
            aluout={Data_width{1'b0}};
            eq=1'b0; 
        end 
        endcase
    end 
endmodule

regfile.sv
module regfile #(
    parameter Data_width=32,Addr_width=5
) (
    input clk, 
    input [Addr_width-1:0] ad1,ad2,ad3,
    input we3,
    input [Data_width-1:0] wd3,
    output [Data_width-1:0] rd1,rd2,
    output [Data_width-1:0] a0 
);
    //Declare 32 registers each 32 bits wide
    logic [Data_width-1:0] register_array [2**Addr_width-1:0];

    //asychronous READ ports
    assign rd1=register_array[ad1];
    assign rd2=register_array[ad2];
    assign a0=register_array[{{Addr_width-4{1'b0}},4'b1010}]; //a0 at position 10 
    //synchronous WRITE ports 
    always_ff @(posedge clk)begin
        if(we3) begin 
            register_array[ad3]<=wd3; 
        end 
    end 
endmodule

sext.sv
module sext #(
    parameter WIDTH = 32
)(
    input logic [WIDTH-1:0] instr,
    input logic [1:0] immsrc,
    output logic [WIDTH-1:0] imm_out
);

always_comb begin
    case (immsrc)
        2'b00: imm_out = {{20{instr[31]}}, instr[31:20]} ;
        2'b10: imm_out = {{20{instr[31]}}, instr[7], instr[30:25], instr[11:8], 1'b0} ;
        default: imm_out = {{20{instr[31]}}, instr[31:20]} ;
    endcase
end

endmodule

ctr_unit.sv
module ctr_unit #(
    parameter IN_WIDTH = 32
)(
    input logic eq,
    input logic [IN_WIDTH-1:0] instr,
    output logic RegWrite,
    output logic [2:0] ALUctrl,
    output logic ALUsrc,
    output logic [1:0] ImmSrc,
    output logic PCsrc,
    output logic data_src
);

always_comb begin
    case (instr[6:2])
        5'b00100: begin // addi
            RegWrite = 1;
            ALUctrl = 3'b0;
            ALUsrc = 1;
            ImmSrc = 2'b00;
            PCsrc = 0;
            data_src = 0;
        end
        5'b11000: begin // bne
            RegWrite = 0;
            ALUctrl = 3'b1;
            ALUsrc = 0;
            ImmSrc = 2'b10;
            if (eq) PCsrc = 0; 
            else PCsrc = 1;
            data_src = 0;
        end
        5'b00000 : begin // lw
            RegWrite = 1;
            ALUctrl = 3'b0;
            ALUsrc = 1;
            ImmSrc = 2'b00;
            PCsrc = 0;
            data_src = 1;
        end
    endcase
end 

endmodule

instr_mem.sv
module instr_mem #(
    parameter WIDTH = 32,
    parameter ADDR_WIDTH = 32,
    parameter RAMZ = 32,
    parameter intFile = "instr.mem"
)(
    input logic [ADDR_WIDTH-1:0] a,
    output logic [WIDTH-1:0] rd
);

logic [WIDTH-1:0] ram [0:RAMZ-1];
initial $readmemh(intFile,ram,0,31);
assign rd = ram[a];

endmodule

riscv.sv
module riscv #(
    parameter WIDTH = 32
)(
    input logic clk,
    input logic rst,
    output logic [WIDTH-1:0] a0
);

logic [WIDTH-1:0] pc;
logic [WIDTH-1:0] next_pc;
logic [WIDTH-1:0] instr;
logic RegWrite;
logic [2:0] ALUctrl;
logic ALUsrc;
logic [1:0] ImmSrc;
logic PCsrc;
logic data_src;
logic [WIDTH-1:0] data_in; 
logic [WIDTH-1:0] data_out; 
logic [WIDTH-1:0] immop;
logic [WIDTH-1:0] aluop1;
logic [WIDTH-1:0] aluop2;
logic [WIDTH-1:0] regop2;
logic [WIDTH-1:0] aluout;
logic [WIDTH-1:0] branch_pc;
logic [WIDTH-1:0] inc_pc;
logic eq;
logic [4:0] rs1;
logic [4:0] rs2;
logic [4:0] rd;

//Assignments
assign rs1 = instr[19:15];
assign rs2 = instr[24:20];
assign rd = instr[11:7];

assign branch_pc = pc + immop;
assign inc_pc = pc + {{WIDTH-3{1'b0}},3'b100};

instr_mem my_instr_mem (
    .a(pc),
    .rd(instr)
);

ctr_unit my_ctr_unit (
    .instr(instr),
    .eq(eq),
    .RegWrite(RegWrite),
    .ALUctrl(ALUctrl),
    .ALUsrc(ALUsrc),
    .ImmSrc(ImmSrc),
    .PCsrc(PCsrc),
    .data_src(data_src)
);

sext my_sext(
    .instr(instr),
    .immsrc(ImmSrc),
    .imm_out(immop)
);

//mux for alu 
mux2to1 my_mux2to1(
    .d0(regop2),
    .d1(immop),
    .out(aluop2),
    .sel(ALUsrc)
);

//register file
regfile my_regfile(
    .clk(clk),
    .ad1(rs1),
    .ad2(rs2),
    .ad3(rd), 
    .we3(RegWrite),
    .wd3(data_in),
    .rd1(aluop1),
    .rd2(regop2),
    .a0(a0)
);
//alu
alu my_alu(
    .aluop1(aluop1),
    .aluop2(aluop2),
    .aluout(aluout),
    .eq(eq),
    .aluctrl(ALUctrl)
);

PCReg my_PCReg(
    .clk(clk),
    .rst(rst),
    .PC(pc),
    .next_PC(next_pc)
);
    
mux2to1 my_mux2to12(
    .d1(branch_pc),
    .d0(inc_pc),
    .out(next_pc),
    .sel(PCsrc)
);

assign data_in = data_src ? data_out : aluout;

data_mem my_data_mem(
    .a(aluout),
    .rd(data_out)
);


endmodule

riscv.vcd
$version Generated by VerilatedVcd $end
$date Wed Nov 22 16:45:57 2023 $end
$timescale 1ps $end

 $scope module TOP $end
  $var wire 32 { a0 [31:0] $end
  $var wire  1 y clk $end
  $var wire  1 z rst $end
  $scope module riscv $end
   $var wire  3 G ALUctrl [2:0] $end
   $var wire  1 H ALUsrc $end
   $var wire  2 I ImmSrc [1:0] $end
   $var wire  1 J PCsrc $end
   $var wire  1 F RegWrite $end
   $var wire 32 | WIDTH [31:0] $end
   $var wire 32 { a0 [31:0] $end
   $var wire 32 O aluop1 [31:0] $end
   $var wire 32 P aluop2 [31:0] $end
   $var wire 32 R aluout [31:0] $end
   $var wire 32 S branch_pc [31:0] $end
   $var wire  1 y clk $end
   $var wire 32 L data_in [31:0] $end
   $var wire 32 M data_out [31:0] $end
   $var wire  1 K data_src $end
   $var wire  1 U eq $end
   $var wire 32 N immop [31:0] $end
   $var wire 32 T inc_pc [31:0] $end
   $var wire 32 E instr [31:0] $end
   $var wire 32 D next_pc [31:0] $end
   $var wire 32 C pc [31:0] $end
   $var wire  5 X rd [4:0] $end
   $var wire 32 Q regop2 [31:0] $end
   $var wire  5 V rs1 [4:0] $end
   $var wire  5 W rs2 [4:0] $end
   $var wire  1 z rst $end
   $scope module my_PCReg $end
    $var wire 32 C PC [31:0] $end
    $var wire 32 | WIDTH [31:0] $end
    $var wire  1 y clk $end
    $var wire 32 D next_PC [31:0] $end
    $var wire  1 z rst $end
   $upscope $end
   $scope module my_alu $end
    $var wire 32 | Data_width [31:0] $end
    $var wire  3 G aluctrl [2:0] $end
    $var wire 32 O aluop1 [31:0] $end
    $var wire 32 P aluop2 [31:0] $end
    $var wire 32 R aluout [31:0] $end
    $var wire  1 U eq $end
   $upscope $end
   $scope module my_ctr_unit $end
    $var wire  3 G ALUctrl [2:0] $end
    $var wire  1 H ALUsrc $end
    $var wire 32 | IN_WIDTH [31:0] $end
    $var wire  2 I ImmSrc [1:0] $end
    $var wire  1 J PCsrc $end
    $var wire  1 F RegWrite $end
    $var wire  1 K data_src $end
    $var wire  1 U eq $end
    $var wire 32 E instr [31:0] $end
   $upscope $end
   $scope module my_data_mem $end
    $var wire 32 | ADDR_WIDTH [31:0] $end
    $var wire 32 } RAMZ [31:0] $end
    $var wire 32 | WIDTH [31:0] $end
    $var wire 32 R a [31:0] $end
    $var wire 64 ~ intFile [63:0] $end
    $var wire 32 M rd [31:0] $end
   $upscope $end
   $scope module my_instr_mem $end
    $var wire 32 | ADDR_WIDTH [31:0] $end
    $var wire 32 | RAMZ [31:0] $end
    $var wire 32 | WIDTH [31:0] $end
    $var wire 32 C a [31:0] $end
    $var wire 72 "! intFile [71:0] $end
    $var wire 32 # ram[0] [31:0] $end
    $var wire 32 - ram[10] [31:0] $end
    $var wire 32 . ram[11] [31:0] $end
    $var wire 32 / ram[12] [31:0] $end
    $var wire 32 0 ram[13] [31:0] $end
    $var wire 32 1 ram[14] [31:0] $end
    $var wire 32 2 ram[15] [31:0] $end
    $var wire 32 3 ram[16] [31:0] $end
    $var wire 32 4 ram[17] [31:0] $end
    $var wire 32 5 ram[18] [31:0] $end
    $var wire 32 6 ram[19] [31:0] $end
    $var wire 32 $ ram[1] [31:0] $end
    $var wire 32 7 ram[20] [31:0] $end
    $var wire 32 8 ram[21] [31:0] $end
    $var wire 32 9 ram[22] [31:0] $end
    $var wire 32 : ram[23] [31:0] $end
    $var wire 32 ; ram[24] [31:0] $end
    $var wire 32 < ram[25] [31:0] $end
    $var wire 32 = ram[26] [31:0] $end
    $var wire 32 > ram[27] [31:0] $end
    $var wire 32 ? ram[28] [31:0] $end
    $var wire 32 @ ram[29] [31:0] $end
    $var wire 32 % ram[2] [31:0] $end
    $var wire 32 A ram[30] [31:0] $end
    $var wire 32 B ram[31] [31:0] $end
    $var wire 32 & ram[3] [31:0] $end
    $var wire 32 ' ram[4] [31:0] $end
    $var wire 32 ( ram[5] [31:0] $end
    $var wire 32 ) ram[6] [31:0] $end
    $var wire 32 * ram[7] [31:0] $end
    $var wire 32 + ram[8] [31:0] $end
    $var wire 32 , ram[9] [31:0] $end
    $var wire 32 E rd [31:0] $end
   $upscope $end
   $scope module my_mux2to1 $end
    $var wire 32 | Data_width [31:0] $end
    $var wire 32 Q d0 [31:0] $end
    $var wire 32 N d1 [31:0] $end
    $var wire 32 P out [31:0] $end
    $var wire  1 H sel $end
   $upscope $end
   $scope module my_mux2to12 $end
    $var wire 32 | Data_width [31:0] $end
    $var wire 32 T d0 [31:0] $end
    $var wire 32 S d1 [31:0] $end
    $var wire 32 D out [31:0] $end
    $var wire  1 J sel $end
   $upscope $end
   $scope module my_regfile $end
    $var wire 32 %! Addr_width [31:0] $end
    $var wire 32 | Data_width [31:0] $end
    $var wire 32 { a0 [31:0] $end
    $var wire  5 V ad1 [4:0] $end
    $var wire  5 W ad2 [4:0] $end
    $var wire  5 X ad3 [4:0] $end
    $var wire  1 y clk $end
    $var wire 32 O rd1 [31:0] $end
    $var wire 32 Q rd2 [31:0] $end
    $var wire 32 Y register_array[0] [31:0] $end
    $var wire 32 c register_array[10] [31:0] $end
    $var wire 32 d register_array[11] [31:0] $end
    $var wire 32 e register_array[12] [31:0] $end
    $var wire 32 f register_array[13] [31:0] $end
    $var wire 32 g register_array[14] [31:0] $end
    $var wire 32 h register_array[15] [31:0] $end
    $var wire 32 i register_array[16] [31:0] $end
    $var wire 32 j register_array[17] [31:0] $end
    $var wire 32 k register_array[18] [31:0] $end
    $var wire 32 l register_array[19] [31:0] $end
    $var wire 32 Z register_array[1] [31:0] $end
    $var wire 32 m register_array[20] [31:0] $end
    $var wire 32 n register_array[21] [31:0] $end
    $var wire 32 o register_array[22] [31:0] $end
    $var wire 32 p register_array[23] [31:0] $end
    $var wire 32 q register_array[24] [31:0] $end
    $var wire 32 r register_array[25] [31:0] $end
    $var wire 32 s register_array[26] [31:0] $end
    $var wire 32 t register_array[27] [31:0] $end
    $var wire 32 u register_array[28] [31:0] $end
    $var wire 32 v register_array[29] [31:0] $end
    $var wire 32 [ register_array[2] [31:0] $end
    $var wire 32 w register_array[30] [31:0] $end
    $var wire 32 x register_array[31] [31:0] $end
    $var wire 32 \ register_array[3] [31:0] $end
    $var wire 32 ] register_array[4] [31:0] $end
    $var wire 32 ^ register_array[5] [31:0] $end
    $var wire 32 _ register_array[6] [31:0] $end
    $var wire 32 ` register_array[7] [31:0] $end
    $var wire 32 a register_array[8] [31:0] $end
    $var wire 32 b register_array[9] [31:0] $end
    $var wire 32 L wd3 [31:0] $end
    $var wire  1 F we3 $end
   $upscope $end
   $scope module my_sext $end
    $var wire 32 | WIDTH [31:0] $end
    $var wire 32 N imm_out [31:0] $end
    $var wire  2 I immsrc [1:0] $end
    $var wire 32 E instr [31:0] $end
   $upscope $end
  $upscope $end
 $upscope $end
$enddefinitions $end


#0
b00000000000000000000000000000000 #
b00000000000000000000000000000000 $
b00000000000000000000000000000000 %
b00000000000000000000000000000000 &
b00000000000000000000000000000000 '
b00000000000000000000000000000000 (
b00000000000000000000000000000000 )
b00000000000000000000000000000000 *
b00000000000000000000000000000000 +
b00000000000000000000000000000000 ,
b00000000000000000000000000000000 -
b00000000000000000000000000000000 .
b00000000000000000000000000000000 /
b00000000000000000000000000000000 0
b00000000000000000000000000000000 1
b00000000000000000000000000000000 2
b00000000000000000000000000000000 3
b00000000000000000000000000000000 4
b00000000000000000000000000000000 5
b00000000000000000000000000000000 6
b00000000000000000000000000000000 7
b00000000000000000000000000000000 8
b00000000000000000000000000000000 9
b00000000000000000000000000000000 :
b00000000000000000000000000000000 ;
b00000000000000000000000000000000 <
b00000000000000000000000000000000 =
b00000000000000000000000000000000 >
b00000000000000000000000000000000 ?
b00000000000000000000000000000000 @
b00000000000000000000000000000000 A
b00000000000000000000000000000000 B
b00000000000000000000000000000000 C
b00000000000000000000000000000100 D
b00000000000000000000000000000000 E
0F
b000 G
0H
b00 I
0J
0K
b00000000000000000000000000000000 L
b00000000000000000000000000000000 M
b00000000000000000000000000000000 N
b00000000000000000000000000000000 O
b00000000000000000000000000000000 P
b00000000000000000000000000000000 Q
b00000000000000000000000000000000 R
b00000000000000000000000000000000 S
b00000000000000000000000000000100 T
0U
b00000 V
b00000 W
b00000 X
b00000000000000000000000000000000 Y
b00000000000000000000000000000000 Z
b00000000000000000000000000000000 [
b00000000000000000000000000000000 \
b00000000000000000000000000000000 ]
b00000000000000000000000000000000 ^
b00000000000000000000000000000000 _
b00000000000000000000000000000000 `
b00000000000000000000000000000000 a
b00000000000000000000000000000000 b
b00000000000000000000000000000000 c
b00000000000000000000000000000000 d
b00000000000000000000000000000000 e
b00000000000000000000000000000000 f
b00000000000000000000000000000000 g
b00000000000000000000000000000000 h
b00000000000000000000000000000000 i
b00000000000000000000000000000000 j
b00000000000000000000000000000000 k
b00000000000000000000000000000000 l
b00000000000000000000000000000000 m
b00000000000000000000000000000000 n
b00000000000000000000000000000000 o
b00000000000000000000000000000000 p
b00000000000000000000000000000000 q
b00000000000000000000000000000000 r
b00000000000000000000000000000000 s
b00000000000000000000000000000000 t
b00000000000000000000000000000000 u
b00000000000000000000000000000000 v
b00000000000000000000000000000000 w
b00000000000000000000000000000000 x
1y
0z
b00000000000000000000000000000000 {
b00000000000000000000000000100000 |
b00000000000000000000000100000000 }
b0110010001100001011101000110000100101110011011010110010101101101 ~
b011010010110111001110011011101000111001000101110011011010110010101101101 "!
b00000000000000000000000000000101 %!
#1
b00001111111100000000001100010011 #
b00000000000000000000010100010011 '
b00000000000000000000010110010011 +
b00000000000001011010010100000011 /
b00000000000101011000010110010011 3
b11111110011001011001110011100011 7
b11111110000000110001100011100011 ;
b00001111111100000000001100010011 E
1F
1H
b00000000000000000000000011111111 L
b00000000000000000000000011111101 M
b00000000000000000000000011111111 N
b00000000000000000000000011111111 P
b00000000000000000000000011111111 R
b00000000000000000000000011111111 S
b11111 W
b00110 X
0y
#2
b00000000000000000000000000000100 C
b00000000000000000000000000001000 D
b00000000000000000000010100010011 E
b00000000000000000000000000000000 L
b00000000000000000000000011111110 M
b00000000000000000000000000000000 N
b00000000000000000000000000000000 P
b00000000000000000000000000000000 R
b00000000000000000000000000000100 S
b00000000000000000000000000001000 T
b00000 W
b01010 X
b00000000000000000000000011111111 _
1y
#3
0y
#4
b00000000000000000000000000001000 C
b00000000000000000000000000001100 D
b00000000000000000000010110010011 E
b00000000000000000000000000001000 S
b00000000000000000000000000001100 T
b01011 X
1y
#5
0y
#6
b00000000000000000000000000001100 C
b00000000000000000000000000010000 D
b00000000000001011010010100000011 E
1K
b00000000000000000000000011111110 L
b00000000000000000000000000001100 S
b00000000000000000000000000010000 T
b01011 V
b01010 X
1y
#7
0y
#8
b00000000000000000000000000010000 C
b00000000000000000000000000010100 D
b00000000000101011000010110010011 E
0K
b00000000000000000000000000000001 L
b00000000000000000000000011111101 M
b00000000000000000000000000000001 N
b00000000000000000000000000000001 P
b00000000000000000000000000000001 R
b00000000000000000000000000010001 S
b00000000000000000000000000010100 T
b00001 W
b01011 X
b00000000000000000000000011111110 c
1y
b00000000000000000000000011111110 {
#9
0y
#10
b00000000000000000000000000010100 C
b00000000000000000000000000001100 D
b11111110011001011001110011100011 E
0F
b001 G
0H
b10 I
1J
b11111111111111111111111111111000 N
b00000000000000000000000000000001 O
b00000000000000000000000011111111 P
b00000000000000000000000011111111 Q
b00000000000000000000000000001100 S
b00000000000000000000000000011000 T
b00110 W
b11001 X
b00000000000000000000000000000001 d
1y
#11
0y
#12
b00000000000000000000000000001100 C
b00000000000000000000000000010000 D
b00000000000001011010010100000011 E
1F
b000 G
1H
b00 I
0J
1K
b00000000000000000000000011111101 L
b00000000000000000000000000000000 N
b00000000000000000000000000000000 P
b00000000000000000000000000000000 Q
b00000000000000000000000000010000 T
b00000 W
b01010 X
1y
#13
0y
#14
b00000000000000000000000000010000 C
b00000000000000000000000000010100 D
b00000000000101011000010110010011 E
0K
b00000000000000000000000000000010 L
b00000000000000000000000000000001 N
b00000000000000000000000000000001 P
b00000000000000000000000000000010 R
b00000000000000000000000000010001 S
b00000000000000000000000000010100 T
b00001 W
b01011 X
b00000000000000000000000011111101 c
1y
b00000000000000000000000011111101 {
#15
0y
#16
b00000000000000000000000000010100 C
b00000000000000000000000000001100 D
b11111110011001011001110011100011 E
0F
b001 G
0H
b10 I
1J
b11111111111111111111111111111000 N
b00000000000000000000000000000010 O
b00000000000000000000000011111111 P
b00000000000000000000000011111111 Q
b00000000000000000000000000001100 S
b00000000000000000000000000011000 T
b00110 W
b11001 X
b00000000000000000000000000000010 d
1y
#17
0y
#18
b00000000000000000000000000001100 C
b00000000000000000000000000010000 D
b00000000000001011010010100000011 E
1F
b000 G
1H
b00 I
0J
1K
b00000000000000000000000011111101 L
b00000000000000000000000000000000 N
b00000000000000000000000000000000 P
b00000000000000000000000000000000 Q
b00000000000000000000000000010000 T
b00000 W
b01010 X
1y
#19
0y
#20
b00000000000000000000000000010000 C
b00000000000000000000000000010100 D
b00000000000101011000010110010011 E
0K
b00000000000000000000000000000011 L
b00000000000000000000000000000001 N
b00000000000000000000000000000001 P
b00000000000000000000000000000011 R
b00000000000000000000000000010001 S
b00000000000000000000000000010100 T
b00001 W
b01011 X
1y
#21
0y
#22
b00000000000000000000000000010100 C
b00000000000000000000000000001100 D
b11111110011001011001110011100011 E
0F
b001 G
0H
b10 I
1J
b11111111111111111111111111111000 N
b00000000000000000000000000000011 O
b00000000000000000000000011111111 P
b00000000000000000000000011111111 Q
b00000000000000000000000000001100 S
b00000000000000000000000000011000 T
b00110 W
b11001 X
b00000000000000000000000000000011 d
1y
#23
0y
#24
b00000000000000000000000000001100 C
b00000000000000000000000000010000 D
b00000000000001011010010100000011 E
1F
b000 G
1H
b00 I
0J
1K
b00000000000000000000000011111101 L
b00000000000000000000000000000000 N
b00000000000000000000000000000000 P
b00000000000000000000000000000000 Q
b00000000000000000000000000010000 T
b00000 W
b01010 X
1y
#25
0y
#26
b00000000000000000000000000010000 C
b00000000000000000000000000010100 D
b00000000000101011000010110010011 E
0K
b00000000000000000000000000000100 L
b00000000000000000000000000000001 N
b00000000000000000000000000000001 P
b00000000000000000000000000000100 R
b00000000000000000000000000010001 S
b00000000000000000000000000010100 T
b00001 W
b01011 X
1y
#27
0y
#28
b00000000000000000000000000010100 C
b00000000000000000000000000001100 D
b11111110011001011001110011100011 E
0F
b001 G
0H
b10 I
1J
b11111111111111111111111111111000 N
b00000000000000000000000000000100 O
b00000000000000000000000011111111 P
b00000000000000000000000011111111 Q
b00000000000000000000000000001100 S
b00000000000000000000000000011000 T
b00110 W
b11001 X
b00000000000000000000000000000100 d
1y
#29
0y
#30
b00000000000000000000000000001100 C
b00000000000000000000000000010000 D
b00000000000001011010010100000011 E
1F
b000 G
1H
b00 I
0J
1K
b00000000000000000000000011111101 L
b00000000000000000000000000000000 N
b00000000000000000000000000000000 P
b00000000000000000000000000000000 Q
b00000000000000000000000000010000 T
b00000 W
b01010 X
1y
#31
0y
#32
b00000000000000000000000000010000 C
b00000000000000000000000000010100 D
b00000000000101011000010110010011 E
0K
b00000000000000000000000000000101 L
b00000000000000000000000000000001 N
b00000000000000000000000000000001 P
b00000000000000000000000000000101 R
b00000000000000000000000000010001 S
b00000000000000000000000000010100 T
b00001 W
b01011 X
1y
#33
0y
#34
b00000000000000000000000000010100 C
b00000000000000000000000000001100 D
b11111110011001011001110011100011 E
0F
b001 G
0H
b10 I
1J
b11111111111111111111111111111000 N
b00000000000000000000000000000101 O
b00000000000000000000000011111111 P
b00000000000000000000000011111111 Q
b00000000000000000000000000001100 S
b00000000000000000000000000011000 T
b00110 W
b11001 X
b00000000000000000000000000000101 d
1y
#35
0y
#36
b00000000000000000000000000001100 C
b00000000000000000000000000010000 D
b00000000000001011010010100000011 E
1F
b000 G
1H
b00 I
0J
1K
b00000000000000000000000011111101 L
b00000000000000000000000000000000 N
b00000000000000000000000000000000 P
b00000000000000000000000000000000 Q
b00000000000000000000000000010000 T
b00000 W
b01010 X
1y
#37
0y
#38
b00000000000000000000000000010000 C
b00000000000000000000000000010100 D
b00000000000101011000010110010011 E
0K
b00000000000000000000000000000110 L
b00000000000000000000000011111100 M
b00000000000000000000000000000001 N
b00000000000000000000000000000001 P
b00000000000000000000000000000110 R
b00000000000000000000000000010001 S
b00000000000000000000000000010100 T
b00001 W
b01011 X
1y
#39
0y
#40
b00000000000000000000000000010100 C
b00000000000000000000000000001100 D
b11111110011001011001110011100011 E
0F
b001 G
0H
b10 I
1J
b11111111111111111111111111111000 N
b00000000000000000000000000000110 O
b00000000000000000000000011111111 P
b00000000000000000000000011111111 Q
b00000000000000000000000000001100 S
b00000000000000000000000000011000 T
b00110 W
b11001 X
b00000000000000000000000000000110 d
1y
#41
0y
#42
b00000000000000000000000000001100 C
b00000000000000000000000000010000 D
b00000000000001011010010100000011 E
1F
b000 G
1H
b00 I
0J
1K
b00000000000000000000000011111100 L
b00000000000000000000000000000000 N
b00000000000000000000000000000000 P
b00000000000000000000000000000000 Q
b00000000000000000000000000010000 T
b00000 W
b01010 X
1y
#43
0y
#44
b00000000000000000000000000010000 C
b00000000000000000000000000010100 D
b00000000000101011000010110010011 E
0K
b00000000000000000000000000000111 L
b00000000000000000000000000000001 N
b00000000000000000000000000000001 P
b00000000000000000000000000000111 R
b00000000000000000000000000010001 S
b00000000000000000000000000010100 T
b00001 W
b01011 X
b00000000000000000000000011111100 c
1y
b00000000000000000000000011111100 {
#45
0y
#46
b00000000000000000000000000010100 C
b00000000000000000000000000001100 D
b11111110011001011001110011100011 E
0F
b001 G
0H
b10 I
1J
b11111111111111111111111111111000 N
b00000000000000000000000000000111 O
b00000000000000000000000011111111 P
b00000000000000000000000011111111 Q
b00000000000000000000000000001100 S
b00000000000000000000000000011000 T
b00110 W
b11001 X
b00000000000000000000000000000111 d
1y
#47
0y
#48
b00000000000000000000000000001100 C
b00000000000000000000000000010000 D
b00000000000001011010010100000011 E
1F
b000 G
1H
b00 I
0J
1K
b00000000000000000000000011111100 L
b00000000000000000000000000000000 N
b00000000000000000000000000000000 P
b00000000000000000000000000000000 Q
b00000000000000000000000000010000 T
b00000 W
b01010 X
1y
#49
0y
#50
b00000000000000000000000000010000 C
b00000000000000000000000000010100 D
b00000000000101011000010110010011 E
0K
b00000000000000000000000000001000 L
b00000000000000000000000011111011 M
b00000000000000000000000000000001 N
b00000000000000000000000000000001 P
b00000000000000000000000000001000 R
b00000000000000000000000000010001 S
b00000000000000000000000000010100 T
b00001 W
b01011 X
1y
#51
0y
#52
b00000000000000000000000000010100 C
b00000000000000000000000000001100 D
b11111110011001011001110011100011 E
0F
b001 G
0H
b10 I
1J
b11111111111111111111111111111000 N
b00000000000000000000000000001000 O
b00000000000000000000000011111111 P
b00000000000000000000000011111111 Q
b00000000000000000000000000001100 S
b00000000000000000000000000011000 T
b00110 W
b11001 X
b00000000000000000000000000001000 d
1y
#53
0y
#54
b00000000000000000000000000001100 C
b00000000000000000000000000010000 D
b00000000000001011010010100000011 E
1F
b000 G
1H
b00 I
0J
1K
b00000000000000000000000011111011 L
b00000000000000000000000000000000 N
b00000000000000000000000000000000 P
b00000000000000000000000000000000 Q
b00000000000000000000000000010000 T
b00000 W
b01010 X
1y
#55
0y
#56
b00000000000000000000000000010000 C
b00000000000000000000000000010100 D
b00000000000101011000010110010011 E
0K
b00000000000000000000000000001001 L
b00000000000000000000000011111010 M
b00000000000000000000000000000001 N
b00000000000000000000000000000001 P
b00000000000000000000000000001001 R
b00000000000000000000000000010001 S
b00000000000000000000000000010100 T
b00001 W
b01011 X
b00000000000000000000000011111011 c
1y
b00000000000000000000000011111011 {
#57
0y
#58
b00000000000000000000000000010100 C
b00000000000000000000000000001100 D
b11111110011001011001110011100011 E
0F
b001 G
0H
b10 I
1J
b11111111111111111111111111111000 N
b00000000000000000000000000001001 O
b00000000000000000000000011111111 P
b00000000000000000000000011111111 Q
b00000000000000000000000000001100 S
b00000000000000000000000000011000 T
b00110 W
b11001 X
b00000000000000000000000000001001 d
1y
#59
0y
#60
b00000000000000000000000000001100 C
b00000000000000000000000000010000 D
b00000000000001011010010100000011 E
1F
b000 G
1H
b00 I
0J
1K
b00000000000000000000000011111010 L
b00000000000000000000000000000000 N
b00000000000000000000000000000000 P
b00000000000000000000000000000000 Q
b00000000000000000000000000010000 T
b00000 W
b01010 X
1y
#61
0y
#62
b00000000000000000000000000010000 C
b00000000000000000000000000010100 D
b00000000000101011000010110010011 E
0K
b00000000000000000000000000001010 L
b00000000000000000000000000000001 N
b00000000000000000000000000000001 P
b00000000000000000000000000001010 R
b00000000000000000000000000010001 S
b00000000000000000000000000010100 T
b00001 W
b01011 X
b00000000000000000000000011111010 c
1y
b00000000000000000000000011111010 {
#63
0y
#64
b00000000000000000000000000010100 C
b00000000000000000000000000001100 D
b11111110011001011001110011100011 E
0F
b001 G
0H
b10 I
1J
b11111111111111111111111111111000 N
b00000000000000000000000000001010 O
b00000000000000000000000011111111 P
b00000000000000000000000011111111 Q
b00000000000000000000000000001100 S
b00000000000000000000000000011000 T
b00110 W
b11001 X
b00000000000000000000000000001010 d
1y
#65
0y
#66
b00000000000000000000000000001100 C
b00000000000000000000000000010000 D
b00000000000001011010010100000011 E
1F
b000 G
1H
b00 I
0J
1K
b00000000000000000000000011111010 L
b00000000000000000000000000000000 N
b00000000000000000000000000000000 P
b00000000000000000000000000000000 Q
b00000000000000000000000000010000 T
b00000 W
b01010 X
1y
#67
0y
#68
b00000000000000000000000000010000 C
b00000000000000000000000000010100 D
b00000000000101011000010110010011 E
0K
b00000000000000000000000000001011 L
b00000000000000000000000011111001 M
b00000000000000000000000000000001 N
b00000000000000000000000000000001 P
b00000000000000000000000000001011 R
b00000000000000000000000000010001 S
b00000000000000000000000000010100 T
b00001 W
b01011 X
1y
#69
0y
#70
b00000000000000000000000000010100 C
b00000000000000000000000000001100 D
b11111110011001011001110011100011 E
0F
b001 G
0H
b10 I
1J
b11111111111111111111111111111000 N
b00000000000000000000000000001011 O
b00000000000000000000000011111111 P
b00000000000000000000000011111111 Q
b00000000000000000000000000001100 S
b00000000000000000000000000011000 T
b00110 W
b11001 X
b00000000000000000000000000001011 d
1y
#71
0y
#72
b00000000000000000000000000001100 C
b00000000000000000000000000010000 D
b00000000000001011010010100000011 E
1F
b000 G
1H
b00 I
0J
1K
b00000000000000000000000011111001 L
b00000000000000000000000000000000 N
b00000000000000000000000000000000 P
b00000000000000000000000000000000 Q
b00000000000000000000000000010000 T
b00000 W
b01010 X
1y
#73
0y
#74
b00000000000000000000000000010000 C
b00000000000000000000000000010100 D
b00000000000101011000010110010011 E
0K
b00000000000000000000000000001100 L
b00000000000000000000000011111000 M
b00000000000000000000000000000001 N
b00000000000000000000000000000001 P
b00000000000000000000000000001100 R
b00000000000000000000000000010001 S
b00000000000000000000000000010100 T
b00001 W
b01011 X
b00000000000000000000000011111001 c
1y
b00000000000000000000000011111001 {
#75
0y
#76
b00000000000000000000000000010100 C
b00000000000000000000000000001100 D
b11111110011001011001110011100011 E
0F
b001 G
0H
b10 I
1J
b11111111111111111111111111111000 N
b00000000000000000000000000001100 O
b00000000000000000000000011111111 P
b00000000000000000000000011111111 Q
b00000000000000000000000000001100 S
b00000000000000000000000000011000 T
b00110 W
b11001 X
b00000000000000000000000000001100 d
1y
#77
0y
#78
b00000000000000000000000000001100 C
b00000000000000000000000000010000 D
b00000000000001011010010100000011 E
1F
b000 G
1H
b00 I
0J
1K
b00000000000000000000000011111000 L
b00000000000000000000000000000000 N
b00000000000000000000000000000000 P
b00000000000000000000000000000000 Q
b00000000000000000000000000010000 T
b00000 W
b01010 X
1y
#79
0y
